README.md
setup.py
WordTreeGenerator/WordTreeGenerator.py
WordTreeGenerator/__init__.py
WordTreeGenerator.egg-info/PKG-INFO
WordTreeGenerator.egg-info/SOURCES.txt
WordTreeGenerator.egg-info/dependency_links.txt
WordTreeGenerator.egg-info/top_level.txt