Metadata-Version: 1.0
Name: WordTreeGenerator
Version: 0.0.2
Summary: Package to generate word tree html
Home-page: UNKNOWN
Author: Renan Santos
Author-email: renans@take.net
License: MIT License
Keywords: Word Tree Data Analysis Html
Platform: UNKNOWN
